terminally_ASPIRED/__init__.py
terminally_ASPIRED/cli.py
terminally_ASPIRED/config_files/defaults.json
terminally_ASPIRED/spectral_reducer.py
terminally_ASPIRED/vendor/__init__.py
terminally_ASPIRED/vendor/aspired_fork/__init__.py
terminally_ASPIRED/vendor/aspired_fork/citation&docs/CITATION.cff
terminally_ASPIRED/vendor/aspired_fork/citation&docs/LICENSE
terminally_ASPIRED/vendor/aspired_fork/citation&docs/MANIFEST.in
terminally_ASPIRED/vendor/aspired_fork/citation&docs/README.md
terminally_ASPIRED/vendor/aspired_fork/citation&docs/package.json
terminally_ASPIRED/vendor/aspired_fork/citation&docs/readthedocs.yml
terminally_ASPIRED/vendor/aspired_fork/extinction/cp_atm_extinct.txt
terminally_ASPIRED/vendor/aspired_fork/extinction/ct_atm_extinct.txt
terminally_ASPIRED/vendor/aspired_fork/extinction/kp_atm_extinct.txt
terminally_ASPIRED/vendor/aspired_fork/extinction/ls_atm_extinct.txt
terminally_ASPIRED/vendor/aspired_fork/extinction/mk_atm_extinct.txt
terminally_ASPIRED/vendor/aspired_fork/extinction/orm_atm_extinct.txt
terminally_ASPIRED/vendor/aspired_fork/extraction.py
terminally_ASPIRED/vendor/aspired_fork/flux_calibration.py
terminally_ASPIRED/vendor/aspired_fork/image_reduction.py
terminally_ASPIRED/vendor/aspired_fork/line_spread_function.py
terminally_ASPIRED/vendor/aspired_fork/onedspec.py
terminally_ASPIRED/vendor/aspired_fork/rascal_fork/__init__.py
terminally_ASPIRED/vendor/aspired_fork/rascal_fork/arc_lines/__init__.py
terminally_ASPIRED/vendor/aspired_fork/rascal_fork/arc_lines/all_nist.csv
terminally_ASPIRED/vendor/aspired_fork/rascal_fork/arc_lines/ar.csv
terminally_ASPIRED/vendor/aspired_fork/rascal_fork/arc_lines/convolve_lines.py
terminally_ASPIRED/vendor/aspired_fork/rascal_fork/arc_lines/cu.csv
terminally_ASPIRED/vendor/aspired_fork/rascal_fork/arc_lines/cuar.csv
terminally_ASPIRED/vendor/aspired_fork/rascal_fork/arc_lines/cuar_unknown.csv
terminally_ASPIRED/vendor/aspired_fork/rascal_fork/arc_lines/cunear_high.csv
terminally_aspired-1.0.0.dist-info/METADATA
terminally_aspired-1.0.0.dist-info/WHEEL
terminally_aspired-1.0.0.dist-info/entry_points.txt
terminally_aspired-1.0.0.dist-info/licenses/LICENSE
terminally_aspired-1.0.0.dist-info/RECORD
