Metadata-Version: 2.4
Name: terminally-aspired
Version: 1.0.0
Summary: CLI for spectral reduction for the SAAO 74 inch using ASPIRED backend
License: MIT
License-File: LICENSE
Author: Francois Campher
Author-email: francois@blackgem.org
Requires-Python: >=3.11,<4.0
Classifier: License :: OSI Approved :: MIT License
Classifier: Programming Language :: Python :: 3
Classifier: Programming Language :: Python :: 3.11
Classifier: Programming Language :: Python :: 3.12
Classifier: Programming Language :: Python :: 3.13
Classifier: Programming Language :: Python :: 3.14
Requires-Dist: astropy (>=4.3)
Requires-Dist: astroscrappy (>=1.1)
Requires-Dist: ccdproc (>=2.3,!=2.4.0)
Requires-Dist: jmespath
Requires-Dist: kaleido (>=0.2)
Requires-Dist: matplotlib (>=3.0.3)
Requires-Dist: numpy (>=1.18)
Requires-Dist: plotly (>=5.6)
Requires-Dist: pynverse (>=0.1.4)
Requires-Dist: scipy (>=1.7)
Requires-Dist: setuptools
Requires-Dist: spectresc (>=1.0.1)
Requires-Dist: specutils (>=1.8)
Requires-Dist: statsmodels (>=0.13)
Requires-Dist: tqdm (>=4.48.0)
